{"version":2,"kind":"Article","sha256":"7e2d3fd0c778931023b15da7fbc944afbd271bc80bcc70a2e48b43d8148bd061","slug":"index","location":"/README.md","dependencies":[],"frontmatter":{"title":"EOFs Cookbook","content_includes_title":false,"authors":[{"id":"Project Pythia Community","name":"Project Pythia Community"}],"open_access":true,"license":{"content":{"id":"CC-BY-4.0","url":"https://creativecommons.org/licenses/by/4.0/","name":"Creative Commons Attribution 4.0 International","free":true,"CC":true},"code":{"id":"Apache-2.0","url":"https://opensource.org/licenses/Apache-2.0","name":"Apache License 2.0","free":true,"osi":true}},"github":"https://github.com/projectpythia/eofs-cookbook","affiliations":[{"id":"UAlbany","name":"University at Albany (SUNY)","department":"Atmospheric and Environmental Sciences","url":"https://www.albany.edu/daes"},{"id":"CISL","name":"NSF National Center for Atmospheric Research","department":"Computational and Information Systems Lab","url":"https://www.cisl.ucar.edu"},{"id":"Unidata","name":"NSF Unidata","url":"https://www.unidata.ucar.edu"},{"id":"Argonne","name":"Argonne National Laboratory","department":"Environmental Science Division","url":"https://www.anl.gov/evs"},{"id":"CarbonPlan","name":"CarbonPlan","url":"https://carbonplan.org"},{"id":"NVIDIA","name":"NVIDIA Corporation","url":"https://www.nvidia.com/"}],"source_url":"https://github.com/projectpythia/eofs-cookbook/blob/main/README.md","edit_url":"https://github.com/projectpythia/eofs-cookbook/edit/main/README.md","thumbnail":"/eofs-cookbook/build/nh-slp-eofs-954dc83c9c79c1c5bd3e33b19efc0cda.png","exports":[{"format":"md","filename":"README.md","url":"/eofs-cookbook/build/README-8f3d6299d87895e4ead5041b3588a4c7.md"}]},"mdast":{"type":"root","children":[{"type":"block","children":[{"type":"image","url":"/eofs-cookbook/build/nh-slp-eofs-954dc83c9c79c1c5bd3e33b19efc0cda.png","alt":"thumbnail","width":800,"key":"XaKfH6U9GB","urlSource":"notebooks/images/nh-slp-eofs.png"},{"type":"paragraph","position":{"start":{"line":5,"column":1},"end":{"line":7,"column":1}},"children":[{"type":"link","url":"https://github.com/ProjectPythia/eofs-cookbook/actions/workflows/nightly-build.yaml","position":{"start":{"line":5,"column":1},"end":{"line":5,"column":1}},"children":[{"type":"image","url":"/eofs-cookbook/build/809cbb88d7880f564c873a170c17abba.svg","alt":"nightly-build","position":{"start":{"line":5,"column":1},"end":{"line":5,"column":1}},"key":"jdgMx63QVp","urlSource":"https://github.com/ProjectPythia/eofs-cookbook/actions/workflows/nightly-build.yaml/badge.svg"}],"urlSource":"https://github.com/ProjectPythia/eofs-cookbook/actions/workflows/nightly-build.yaml","error":true,"key":"Tm2pS2duTO"},{"type":"text","value":"\n","position":{"start":{"line":5,"column":1},"end":{"line":5,"column":1}},"key":"YNfsVp0Ssw"},{"type":"link","url":"https://binder.projectpythia.org/v2/gh/ProjectPythia/eofs-cookbook/main?labpath=notebooks","position":{"start":{"line":5,"column":1},"end":{"line":5,"column":1}},"children":[{"type":"image","url":"/eofs-cookbook/build/31e3f387ea168934ca949c27e9927ea4.svg","alt":"Binder","position":{"start":{"line":5,"column":1},"end":{"line":5,"column":1}},"key":"aE3Beq0Th6","urlSource":"https://binder.projectpythia.org/badge_logo.svg"}],"urlSource":"https://binder.projectpythia.org/v2/gh/ProjectPythia/eofs-cookbook/main?labpath=notebooks","key":"pXmzIvSQKB"},{"type":"text","value":"\n","position":{"start":{"line":5,"column":1},"end":{"line":5,"column":1}},"key":"mtt6abvLGK"},{"type":"cite","url":"https://doi.org/10.5281/zenodo.10909812","position":{"start":{"line":5,"column":1},"end":{"line":5,"column":1}},"children":[{"type":"image","url":"/eofs-cookbook/build/722d16dfaa62bc94d3448fc5b4dfc33e.svg","alt":"DOI","position":{"start":{"line":5,"column":1},"end":{"line":5,"column":1}},"key":"kG7FQzrcW1","urlSource":"https://zenodo.org/badge/DOI/10.5281/zenodo.10909812.svg"}],"kind":"narrative","label":"https://doi.org/10.5281/zenodo.10909812","identifier":"https://doi.org/10.5281/zenodo.10909812","enumerator":"1","key":"P7T6gXUi8t"}],"key":"sUIvRURise"},{"type":"paragraph","position":{"start":{"line":10,"column":1},"end":{"line":10,"column":1}},"children":[{"type":"text","value":"This Project Pythia Cookbook covers empirical orthogonal function analysis and its application to climate data.","position":{"start":{"line":10,"column":1},"end":{"line":10,"column":1}},"key":"g6nzR6Q5PV"}],"key":"l3pqePHapC"},{"type":"heading","depth":2,"position":{"start":{"line":12,"column":1},"end":{"line":12,"column":1}},"children":[{"type":"text","value":"Motivation","position":{"start":{"line":12,"column":1},"end":{"line":12,"column":1}},"key":"JUIEHmuce9"}],"identifier":"motivation","label":"Motivation","html_id":"motivation","implicit":true,"key":"mIkKByEdDf"},{"type":"paragraph","position":{"start":{"line":14,"column":1},"end":{"line":14,"column":1}},"children":[{"type":"text","value":"Empirical orthogonal function (EOF) analysis is an essential tool for studying the variability of the atmosphere–ocean system. Meteorological and oceanographic data is noisy and multidimensional, but an EOF analysis allows us to pull out patterns from the data that might otherwise be difficult to find. The goal of this cookbook is to provide background and context to the analysis alongside practical examples of carrying out the analysis using Python packages.","position":{"start":{"line":14,"column":1},"end":{"line":14,"column":1}},"key":"FBB8wx80yw"}],"key":"y5aG6y6sfp"},{"type":"heading","depth":2,"position":{"start":{"line":16,"column":1},"end":{"line":16,"column":1}},"children":[{"type":"text","value":"Authors","position":{"start":{"line":16,"column":1},"end":{"line":16,"column":1}},"key":"yoD0ZMO5QJ"}],"identifier":"authors","label":"Authors","html_id":"authors","implicit":true,"key":"pE13sQd6kC"},{"type":"paragraph","position":{"start":{"line":18,"column":1},"end":{"line":18,"column":1}},"children":[{"type":"link","url":"https://github.com/r-ford","position":{"start":{"line":18,"column":1},"end":{"line":18,"column":1}},"children":[{"type":"text","value":"Robert Ford","position":{"start":{"line":18,"column":1},"end":{"line":18,"column":1}},"key":"QFB6JznMto"}],"urlSource":"https://github.com/r-ford","error":true,"key":"VU3bODAkgl"}],"key":"IPnLtnxMlz"},{"type":"heading","depth":3,"position":{"start":{"line":20,"column":1},"end":{"line":20,"column":1}},"children":[{"type":"text","value":"Contributors","position":{"start":{"line":20,"column":1},"end":{"line":20,"column":1}},"key":"CKlLGdKwic"}],"identifier":"contributors","label":"Contributors","html_id":"contributors","implicit":true,"key":"qjHrS8aIcR"},{"type":"link","url":"https://github.com/ProjectPythia/eofs-cookbook/graphs/contributors","children":[{"type":"image","url":"/eofs-cookbook/build/1546c1bbf912ca81fc0a87dedf11b814.svg","key":"ni9ViK0QRb","urlSource":"https://contrib.rocks/image?repo=ProjectPythia/eofs-cookbook"}],"urlSource":"https://github.com/ProjectPythia/eofs-cookbook/graphs/contributors","error":true,"key":"wPrJd6EcOU"},{"type":"heading","depth":2,"position":{"start":{"line":26,"column":1},"end":{"line":26,"column":1}},"children":[{"type":"text","value":"Structure","position":{"start":{"line":26,"column":1},"end":{"line":26,"column":1}},"key":"Dcr1f4FBgW"}],"identifier":"structure","label":"Structure","html_id":"structure","implicit":true,"key":"dLgWaROqrv"},{"type":"paragraph","position":{"start":{"line":28,"column":1},"end":{"line":28,"column":1}},"children":[{"type":"text","value":"This cookbook currently has one section that covers the basics of EOF analysis.","position":{"start":{"line":28,"column":1},"end":{"line":28,"column":1}},"key":"Pr6eQNReh0"}],"key":"HPT8PBW1Ud"},{"type":"heading","depth":3,"position":{"start":{"line":30,"column":1},"end":{"line":30,"column":1}},"children":[{"type":"text","value":"Foundations","position":{"start":{"line":30,"column":1},"end":{"line":30,"column":1}},"key":"tEMskkOPUu"}],"identifier":"foundations","label":"Foundations","html_id":"foundations","implicit":true,"key":"kCBQ9Nr2Mf"},{"type":"paragraph","position":{"start":{"line":32,"column":1},"end":{"line":32,"column":1}},"children":[{"type":"text","value":"This section includes three notebooks:","position":{"start":{"line":32,"column":1},"end":{"line":32,"column":1}},"key":"zyCudZZz1Q"}],"key":"XEtEPNSW4p"},{"type":"list","ordered":false,"spread":false,"position":{"start":{"line":33,"column":1},"end":{"line":36,"column":1}},"children":[{"type":"listItem","spread":true,"position":{"start":{"line":33,"column":1},"end":{"line":33,"column":1}},"children":[{"type":"paragraph","children":[{"type":"text","value":"Introduction to EOFs","position":{"start":{"line":33,"column":1},"end":{"line":33,"column":1}},"key":"LhhZCGlOJQ"}],"key":"F1i80phCgL"}],"key":"ibq1ASicV0"},{"type":"listItem","spread":true,"position":{"start":{"line":34,"column":1},"end":{"line":34,"column":1}},"children":[{"type":"paragraph","children":[{"type":"text","value":"EOFs with NumPy","position":{"start":{"line":34,"column":1},"end":{"line":34,"column":1}},"key":"l49FUzKRE5"}],"key":"h7skGUbduA"}],"key":"fAv6hnllcw"},{"type":"listItem","spread":true,"position":{"start":{"line":35,"column":1},"end":{"line":36,"column":1}},"children":[{"type":"paragraph","children":[{"type":"text","value":"Finding Climate Modes with EOFs","position":{"start":{"line":35,"column":1},"end":{"line":35,"column":1}},"key":"LrQGlEl7AD"}],"key":"XZraOAOjzP"}],"key":"S4ONzAM7GN"}],"key":"zqHhZhhKwL"},{"type":"heading","depth":2,"position":{"start":{"line":37,"column":1},"end":{"line":37,"column":1}},"children":[{"type":"text","value":"Running the Notebooks","position":{"start":{"line":37,"column":1},"end":{"line":37,"column":1}},"key":"uUF4xFPSEp"}],"identifier":"running-the-notebooks","label":"Running the Notebooks","html_id":"running-the-notebooks","implicit":true,"key":"aEBdVG4X14"},{"type":"paragraph","position":{"start":{"line":39,"column":1},"end":{"line":39,"column":1}},"children":[{"type":"text","value":"You can either run the notebook using ","position":{"start":{"line":39,"column":1},"end":{"line":39,"column":1}},"key":"LAb3QUvBbP"},{"type":"link","url":"https://binder.projectpythia.org/","position":{"start":{"line":39,"column":1},"end":{"line":39,"column":1}},"children":[{"type":"text","value":"Binder","position":{"start":{"line":39,"column":1},"end":{"line":39,"column":1}},"key":"Gs5Tg0tvP2"}],"urlSource":"https://binder.projectpythia.org/","key":"l67JA9154E"},{"type":"text","value":" or on your local machine.","position":{"start":{"line":39,"column":1},"end":{"line":39,"column":1}},"key":"rRAvfhc91v"}],"key":"A7i3gYztp8"},{"type":"heading","depth":3,"position":{"start":{"line":41,"column":1},"end":{"line":41,"column":1}},"children":[{"type":"text","value":"Running on Binder","position":{"start":{"line":41,"column":1},"end":{"line":41,"column":1}},"key":"hRi36WqDcU"}],"identifier":"running-on-binder","label":"Running on Binder","html_id":"running-on-binder","implicit":true,"key":"SDRqLC8nZU"},{"type":"paragraph","position":{"start":{"line":43,"column":1},"end":{"line":56,"column":1}},"children":[{"type":"text","value":"The simplest way to interact with a Jupyter Notebook is through\n","position":{"start":{"line":43,"column":1},"end":{"line":43,"column":1}},"key":"PGbDFdZVY9"},{"type":"link","url":"https://binder.projectpythia.org/","position":{"start":{"line":43,"column":1},"end":{"line":43,"column":1}},"children":[{"type":"text","value":"Binder","position":{"start":{"line":43,"column":1},"end":{"line":43,"column":1}},"key":"FUh9N2CsnH"}],"urlSource":"https://binder.projectpythia.org/","key":"RTF5K2eLVU"},{"type":"text","value":", which enables the execution of a\n","position":{"start":{"line":43,"column":1},"end":{"line":43,"column":1}},"key":"jkC0aGSbeD"},{"type":"link","url":"https://jupyterbook.org","position":{"start":{"line":43,"column":1},"end":{"line":43,"column":1}},"children":[{"type":"text","value":"Jupyter Book","position":{"start":{"line":43,"column":1},"end":{"line":43,"column":1}},"key":"J3R1A9ydQD"}],"urlSource":"https://jupyterbook.org","key":"NvDPHdPsOQ"},{"type":"text","value":" in the cloud. The details of how this works are not\nimportant for now. All you need to know is how to launch a Pythia\nCookbooks chapter via Binder. Simply navigate your mouse to\nthe top right corner of the book chapter you are viewing and click\non the rocket ship icon, (see figure below), and be sure to select\n“launch Binder”. After a moment you should be presented with a\nnotebook that you can interact with. I.e. you’ll be able to execute\nand even change the example programs. You’ll see that the code cells\nhave no output at first, until you execute them by pressing\n","position":{"start":{"line":43,"column":1},"end":{"line":43,"column":1}},"key":"TbLjCWyBe5"},{"type":"keyboard","children":[{"type":"text","value":"Shift","key":"VhX91hCSuK"}],"key":"vlDlWGm3vp"},{"type":"text","value":"+","position":{"start":{"line":43,"column":1},"end":{"line":43,"column":1}},"key":"BK4jBLGTFY"},{"type":"keyboard","children":[{"type":"text","value":"Enter","key":"c2fovnlB3F"}],"key":"AypCqLeyw6"},{"type":"text","value":". Complete details on how to interact with\na live Jupyter notebook are described in ","position":{"start":{"line":43,"column":1},"end":{"line":43,"column":1}},"key":"zgEUchtO9Y"},{"type":"link","url":"https://foundations.projectpythia.org/foundations/getting-started-jupyter","position":{"start":{"line":43,"column":1},"end":{"line":43,"column":1}},"children":[{"type":"text","value":"Getting Started with\nJupyter","position":{"start":{"line":43,"column":1},"end":{"line":43,"column":1}},"key":"HC8k6hAih9"}],"urlSource":"https://foundations.projectpythia.org/foundations/getting-started-jupyter","key":"zAFnkvZcat"},{"type":"text","value":".","position":{"start":{"line":43,"column":1},"end":{"line":43,"column":1}},"key":"u5426JpWHW"}],"key":"IvBiD3QCIt"},{"type":"heading","depth":3,"position":{"start":{"line":58,"column":1},"end":{"line":58,"column":1}},"children":[{"type":"text","value":"Running on Your Own Machine","position":{"start":{"line":58,"column":1},"end":{"line":58,"column":1}},"key":"KFgt1Aob6U"}],"identifier":"running-on-your-own-machine","label":"Running on Your Own Machine","html_id":"running-on-your-own-machine","implicit":true,"key":"VXKAwHw6tB"},{"type":"paragraph","position":{"start":{"line":60,"column":1},"end":{"line":60,"column":1}},"children":[{"type":"text","value":"If you are interested in running this material locally on your computer, you will need to follow this workflow:","position":{"start":{"line":60,"column":1},"end":{"line":60,"column":1}},"key":"ieAVzxXkB8"}],"key":"hGQqDOli3T"},{"type":"list","ordered":true,"start":1,"spread":false,"position":{"start":{"line":62,"column":1},"end":{"line":81,"column":1}},"children":[{"type":"listItem","spread":true,"position":{"start":{"line":62,"column":1},"end":{"line":67,"column":1}},"children":[{"type":"paragraph","position":{"start":{"line":62,"column":1},"end":{"line":62,"column":1}},"children":[{"type":"text","value":"Clone the ","position":{"start":{"line":62,"column":1},"end":{"line":62,"column":1}},"key":"YlaL1oInrB"},{"type":"inlineCode","value":"https://github.com/ProjectPythia/eofs-cookbook","position":{"start":{"line":62,"column":1},"end":{"line":62,"column":1}},"key":"qvACCELha6"},{"type":"text","value":" repository:","position":{"start":{"line":62,"column":1},"end":{"line":62,"column":1}},"key":"Lhbr0B9apa"}],"key":"r9RcbijOYv"},{"type":"code","lang":"bash","value":" git clone https://github.com/ProjectPythia/eofs-cookbook.git","position":{"start":{"line":64,"column":1},"end":{"line":66,"column":1}},"key":"fTjIP0iRgE"}],"key":"jd4fAFHeRD"},{"type":"listItem","spread":true,"position":{"start":{"line":68,"column":1},"end":{"line":71,"column":1}},"children":[{"type":"paragraph","position":{"start":{"line":68,"column":1},"end":{"line":68,"column":1}},"children":[{"type":"text","value":"Move into the ","position":{"start":{"line":68,"column":1},"end":{"line":68,"column":1}},"key":"tmUu3Ot7sE"},{"type":"inlineCode","value":"eofs-cookbook","position":{"start":{"line":68,"column":1},"end":{"line":68,"column":1}},"key":"ypbL7AYBeB"},{"type":"text","value":" directory","position":{"start":{"line":68,"column":1},"end":{"line":68,"column":1}},"key":"w55YD7CV01"}],"key":"JNgH4yED3E"},{"type":"code","lang":"bash","value":"cd eofs-cookbook","position":{"start":{"line":69,"column":1},"end":{"line":71,"column":1}},"key":"WXjIZNgqco"}],"key":"JnuFPlbQWj"},{"type":"listItem","spread":true,"position":{"start":{"line":72,"column":1},"end":{"line":76,"column":1}},"children":[{"type":"paragraph","position":{"start":{"line":72,"column":1},"end":{"line":72,"column":1}},"children":[{"type":"text","value":"Create and activate your conda environment from the ","position":{"start":{"line":72,"column":1},"end":{"line":72,"column":1}},"key":"kgGk5MZ5Sl"},{"type":"inlineCode","value":"environment.yml","position":{"start":{"line":72,"column":1},"end":{"line":72,"column":1}},"key":"WbXDnwHCv8"},{"type":"text","value":" file","position":{"start":{"line":72,"column":1},"end":{"line":72,"column":1}},"key":"mfLD1RDcnD"}],"key":"epyqL9McVk"},{"type":"code","lang":"bash","value":"conda env create -f environment.yml\nconda activate eofs-cookbook-dev","position":{"start":{"line":73,"column":1},"end":{"line":76,"column":1}},"key":"B55jW3X8pW"}],"key":"QmP7iSobqh"},{"type":"listItem","spread":true,"position":{"start":{"line":77,"column":1},"end":{"line":81,"column":1}},"children":[{"type":"paragraph","position":{"start":{"line":77,"column":1},"end":{"line":77,"column":1}},"children":[{"type":"text","value":"Move into the ","position":{"start":{"line":77,"column":1},"end":{"line":77,"column":1}},"key":"I7XoYSk16B"},{"type":"inlineCode","value":"notebooks","position":{"start":{"line":77,"column":1},"end":{"line":77,"column":1}},"key":"yx50BaguUx"},{"type":"text","value":" directory and start up Jupyterlab","position":{"start":{"line":77,"column":1},"end":{"line":77,"column":1}},"key":"ZL3qAYTcEd"}],"key":"LnNXz3PTYr"},{"type":"code","lang":"bash","value":"cd notebooks/\njupyter lab","position":{"start":{"line":78,"column":1},"end":{"line":81,"column":1}},"key":"iS6fyLq1l7"}],"key":"OcVMSBC6sZ"}],"key":"F1RR9R3s0h"}],"key":"YtEMMQMhBY"}],"key":"VicnqGCL08"},"references":{"cite":{"order":["https://doi.org/10.5281/zenodo.10909812"],"data":{"https://doi.org/10.5281/zenodo.10909812":{"label":"https://doi.org/10.5281/zenodo.10909812","enumerator":"1","doi":"10.5281/ZENODO.10909812","html":"Ford, R. R., & EOFs Cookbook contributors. (2025). <i>EOFs Cookbook</i>. Zenodo. <a target=\"_blank\" rel=\"noreferrer\" href=\"https://doi.org/10.5281/ZENODO.10909812\">10.5281/ZENODO.10909812</a>","url":"https://doi.org/10.5281/ZENODO.10909812"}}}},"footer":{"navigation":{"next":{"title":"How to Cite This Cookbook","url":"/notebooks/how-to-cite","group":"Preamble"}}},"domain":"http://localhost:3000"}